{
  "fingerprint": null,
  "sections": {
    "smart_meter": {
      "templateId": "smart_meter",
      "name": "Kostal – smart meter",
      "entries": {
        "total_active_power": {
          "startAddress": 252,
          "size": 2,
          "scaleFactor": 1,
          "formula": "x",
          "parameterType": {
            "primitive": "float32s"
          },
          "operationType": "READ_HOLDING_REGISTER",
          "byteOrder": "BIG_ENDIAN"
        },
        "total_imported": {
          "startAddress": 252,
          "size": 2,
          "scaleFactor": 1,
          "formula": "0",
          "parameterType": {
            "primitive": "float32s"
          },
          "operationType": "READ_HOLDING_REGISTER",
          "byteOrder": "BIG_ENDIAN"
        },
        "total_exported": {
          "startAddress": 252,
          "size": 2,
          "scaleFactor": 1,
          "formula": "0",
          "parameterType": {
            "primitive": "float32s"
          },
          "operationType": "READ_HOLDING_REGISTER",
          "byteOrder": "BIG_ENDIAN"
        },
        "power_l1": {
          "startAddress": 252,
          "size": 2,
          "scaleFactor": 1,
          "formula": "0",
          "parameterType": {
            "primitive": "float32s"
          },
          "operationType": "READ_HOLDING_REGISTER",
          "byteOrder": "BIG_ENDIAN"
        },
        "power_l2": {
          "startAddress": 252,
          "size": 2,
          "scaleFactor": 1,
          "formula": "0",
          "parameterType": {
            "primitive": "float32s"
          },
          "operationType": "READ_HOLDING_REGISTER",
          "byteOrder": "BIG_ENDIAN"
        },
        "power_l3": {
          "startAddress": 252,
          "size": 2,
          "scaleFactor": 1,
          "formula": "0",
          "parameterType": {
            "primitive": "float32s"
          },
          "operationType": "READ_HOLDING_REGISTER",
          "byteOrder": "BIG_ENDIAN"
        },
        "voltage_l1": {
          "startAddress": 252,
          "size": 2,
          "scaleFactor": 1,
          "formula": "0",
          "parameterType": {
            "primitive": "float32s"
          },
          "operationType": "READ_HOLDING_REGISTER",
          "byteOrder": "BIG_ENDIAN"
        },
        "voltage_l2": {
          "startAddress": 252,
          "size": 2,
          "scaleFactor": 1,
          "formula": "0",
          "parameterType": {
            "primitive": "float32s"
          },
          "operationType": "READ_HOLDING_REGISTER",
          "byteOrder": "BIG_ENDIAN"
        },
        "voltage_l3": {
          "startAddress": 252,
          "size": 2,
          "scaleFactor": 1,
          "formula": "0",
          "parameterType": {
            "primitive": "float32s"
          },
          "operationType": "READ_HOLDING_REGISTER",
          "byteOrder": "BIG_ENDIAN"
        }
      }
    }
  },
  "addressOffset": 0
}
